curl_to_requests/__init__.py
curl_to_requests/curl_help.py
curl_to_requests/curl_to_requests.py
curl_to_requests-1.0.1.dist-info/DESCRIPTION.rst
curl_to_requests-1.0.1.dist-info/METADATA
curl_to_requests-1.0.1.dist-info/metadata.json
curl_to_requests-1.0.1.dist-info/RECORD
curl_to_requests-1.0.1.dist-info/top_level.txt
curl_to_requests-1.0.1.dist-info/WHEEL
