Metadata-Version: 2.0
Name: curl-to-requests
Version: 1.0.1
Summary: Converts cURL commands into equivalent Python Requests code
Home-page: https://github.com/mosesschwartz/curl_to_requests
Author: Moses Schwartz, Bechtel CIRT
Author-email: moses.schwartz@gmail.com
License: MIT
Keywords: curl requests converter rest api
Platform: UNKNOWN
Classifier: Development Status :: 3 - Alpha
Classifier: Intended Audience :: Developers
Classifier: Topic :: Software Development
Classifier: Topic :: Utilities
Classifier: License :: OSI Approved :: MIT License
Classifier: Programming Language :: Python :: 2
Classifier: Programming Language :: Python :: 2.7
Provides-Extra: test
Provides-Extra: dev
